python_solumclient-3.8.0.data/scripts/solum-app-setup.py
solumclient/__init__.py
solumclient/client.py
solumclient/config.py
solumclient/i18n.py
solumclient/solum.py
solumclient/builder/__init__.py
solumclient/builder/client.py
solumclient/builder/v1/__init__.py
solumclient/builder/v1/client.py
solumclient/builder/v1/image.py
solumclient/common/__init__.py
solumclient/common/auth.py
solumclient/common/base.py
solumclient/common/cli_utils.py
solumclient/common/client.py
solumclient/common/cliutils.py
solumclient/common/exc.py
solumclient/common/github.py
solumclient/common/yamlutils.py
solumclient/common/apiclient/__init__.py
solumclient/common/apiclient/auth.py
solumclient/common/apiclient/base.py
solumclient/common/apiclient/client.py
solumclient/common/apiclient/exceptions.py
solumclient/common/apiclient/fake_client.py
solumclient/locale/en_GB/LC_MESSAGES/solumclient.po
solumclient/tests/__init__.py
solumclient/tests/base.py
solumclient/tests/test_client.py
solumclient/tests/test_solum.py
solumclient/tests/builder/__init__.py
solumclient/tests/builder/test_client.py
solumclient/tests/builder/v1/__init__.py
solumclient/tests/builder/v1/test_image.py
solumclient/tests/common/__init__.py
solumclient/tests/common/test_auth.py
solumclient/tests/common/test_base.py
solumclient/tests/common/test_client.py
solumclient/tests/common/test_cliutils.py
solumclient/tests/common/test_exc.py
solumclient/tests/common/test_github.py
solumclient/tests/common/test_yamlutils.py
solumclient/tests/v1/__init__.py
solumclient/tests/v1/test_component.py
solumclient/tests/v1/test_languagepack.py
solumclient/tests/v1/test_pipeline.py
solumclient/tests/v1/test_plan.py
solumclient/tests/v1/test_platform.py
solumclient/v1/__init__.py
solumclient/v1/app.py
solumclient/v1/client.py
solumclient/v1/component.py
solumclient/v1/languagepack.py
solumclient/v1/pipeline.py
solumclient/v1/plan.py
solumclient/v1/platform.py
solumclient/v1/workflow.py
python_solumclient-3.8.0.dist-info/AUTHORS
python_solumclient-3.8.0.dist-info/LICENSE
python_solumclient-3.8.0.dist-info/METADATA
python_solumclient-3.8.0.dist-info/WHEEL
python_solumclient-3.8.0.dist-info/entry_points.txt
python_solumclient-3.8.0.dist-info/pbr.json
python_solumclient-3.8.0.dist-info/top_level.txt
python_solumclient-3.8.0.dist-info/RECORD
