Metadata-Version: 2.1
Name: python-solumclient
Version: 3.8.0
Summary: Client library for Solum API
Home-page: https://docs.openstack.org/python-solumclient/latest/
Author: OpenStack
Author-email: openstack-discuss@lists.openstack.org
License: UNKNOWN
Platform: UNKNOWN
Classifier: Environment :: OpenStack
Classifier: Intended Audience :: Information Technology
Classifier: Intended Audience :: System Administrators
Classifier: License :: OSI Approved :: Apache Software License
Classifier: Operating System :: POSIX :: Linux
Classifier: Programming Language :: Python
Classifier: Programming Language :: Python :: Implementation :: CPython
Classifier: Programming Language :: Python :: 3 :: Only
Classifier: Programming Language :: Python :: 3
Classifier: Programming Language :: Python :: 3.6
Classifier: Programming Language :: Python :: 3.7
Classifier: Programming Language :: Python :: 3.8
Requires-Python: >=3.6
Requires-Dist: Babel (!=2.4.0,>=2.3.4)
Requires-Dist: PrettyTable (>=0.7.2)
Requires-Dist: PyYAML (>=3.13)
Requires-Dist: debtcollector (>=1.2.0)
Requires-Dist: httplib2 (>=0.18.1)
Requires-Dist: iso8601 (>=0.1.11)
Requires-Dist: jsonschema (>=3.2.0)
Requires-Dist: oslo.config (>=5.2.0)
Requires-Dist: oslo.i18n (>=3.15.3)
Requires-Dist: oslo.log (>=3.36.0)
Requires-Dist: oslo.utils (>=3.33.0)
Requires-Dist: pbr (!=2.1.0,>=2.0.0)
Requires-Dist: python-keystoneclient (>=3.8.0)
Requires-Dist: requests (>=2.14.2)
Requires-Dist: stevedore (>=2.0.1)
